url_tricks/__init__.py
url_tricks/google.py
url_tricks-0.0.2.dist-info/METADATA
url_tricks-0.0.2.dist-info/WHEEL
url_tricks-0.0.2.dist-info/top_level.txt
url_tricks-0.0.2.dist-info/RECORD
