Metadata-Version: 2.1
Name: url-tricks
Version: 0.0.2
Summary: URL Manipulations that is widely used
Home-page: https://github.com/randikabanura/url_tricks
Author: Banura Randika Perera
Author-email: <randika.banura@gmail.com>
License: MIT
Keywords: python,tricks,url,string,manipulation,fun
Platform: UNKNOWN
Classifier: Development Status :: 1 - Planning
Classifier: Intended Audience :: Developers
Classifier: Programming Language :: Python :: 3
Classifier: Operating System :: Unix
Classifier: Operating System :: MacOS :: MacOS X
Classifier: Operating System :: Microsoft :: Windows
